{"pageContext":{"isCreatedByStatefulCreatePages":false,"id":"shortcut-sblm3-win","data":{"id":"shortcut-sblm3-win","title":"সাবলাইম টেক্সট ৩(উইন্ডোজ)","slug":"shortcut-sblm3-win","description":"সাবলাইম টেক্সট ৩ এর প্রয়োজনী উইন্ডোজ শর্টকাট কী","colorPref":"#333","contents":[{"title":"সাধারণ","items":[{"definition":"কমান্ড প্যালেট","code":"Ctrl + Shift + P"},{"definition":"কন্সোল দেখানো বা লুকানো","code":"Ctrl + `"},{"definition":"সাইডবার দেখানো বা লুকানো","code":"Ctrl + K, B"},{"definition":"শেষ কী-বোর্ড শর্টকাটটা আবার অ্যাপ্লাই করতে","code":"Ctrl + Y"},{"definition":"অটোকমপ্লিট সাজেশন সিলেক্ট করতে","code":"Ctrl + Space"}]},{"title":"উইন্ডো ম্যানিপুলেশন","items":[{"definition":"ফুল-স্ক্রিন","code":"F11"},{"definition":"ঝামেলামুক্ত মোড","code":"Shift + F11"},{"definition":"নতুন উইন্ডো","code":"Ctrl + Shift + N"},{"definition":"নতুন ট্যাব","code":"Ctrl + N"},{"definition":"একটা ট্যাব সিলেক্ট করা","code":"Alt + ট্যাব নাম্বার"},{"definition":"ট্যাব ক্লোজ করা","code":"Ctrl + W"},{"definition":"ট্যাব প্যানে সরানো","code":"Ctrl + Shift + প্যান নাম্বার"},{"definition":"প্যানে সুইচ করা","code":"Ctrl + প্যান নাম্বার"}]},{"title":"লে-আউট","items":[{"definition":"২, ৩, ৪ টা কলাম","code":"Alt + Shift + 1/4"},{"definition":"২ অথবা ৩ টা রো","code":"Alt + Shift + 8/9"},{"definition":"৪টা গ্রিড","code":"Alt + Shift + 5"},{"definition":"প্যান সমান দুইভাগে ভাগ করা","code":"Ctrl + K, Ctrl + Shift + আপ কী"}]},{"title":"প্যান ম্যানিপুলেশন","items":[{"definition":"প্যানেলে যাওয়া","code":"Ctrl + প্যানেল নাম্বার"},{"definition":"ফাইল প্যানেলে নেওয়া","code":"Ctrl + + Shift + প্যানেল নাম্বার"}]},{"title":"ন্যাভিগেশন","items":[{"definition":"ফাইল ওপেন করুন","code":"Ctrl + P"},{"definition":"সিম্বল খোঁজা","code":"Ctrl + P, @"},{"definition":"কোনো সিম্বলে যাওয়া","code":"Ctrl + R"},{"definition":"লাইনে যাওয়া","code":"Ctrl + G"},{"definition":"পরের ট্যাবে যাওয়া","code":"Ctrl + Pgdn"},{"definition":"আগের ট্যাবে যাওয়া","code":"Ctrl + Pgup"},{"definition":"ক্লোজ ব্র্যাকেটে জাম্প করা","code":"Ctrl + M"}]},{"title":"খোঁজা এবং রিপ্লেস","items":[{"definition":"খোঁজা","code":"Ctrl + F"},{"definition":"পরে অংশে আরো খোঁজা","code":"F3"},{"definition":"আগের অংশ থেকে খোঁজা","code":"Shift + F3"},{"definition":"সবগুলো সিলেকশন রিপ্লেস করা","code":"সিলেক্ট করা পর, Alt + F3"},{"definition":"রিপ্লেস","code":"Ctrl + H"},{"definition":"ইনক্রিমেন্টার খোঁজাখুঁজি","code":"Ctrl + I"},{"definition":"কোনো ফাইলে খোঁজা","code":"Ctrl + Shift + F"},{"definition":"খোঁজা এবং একই সাথে কয়েকটা এডিট করা","code":"Ctrl + F, Alt + Enter"},{"definition":"সিলেক্ট করা টেক্সট দিয়ে খোঁজা","code":"Ctrl + E"},{"definition":"সিলেক্ট করা টেক্সট দিয়ে রিপ্লেস করা","code":"Ctrl + Shift + E"}]},{"title":"টেক্সট সিলেক্ট","items":[{"definition":"লাইন","code":"Ctrl + L"},{"definition":"শব্দ","code":"Ctrl + D"},{"definition":"পরের সেইম টেক্সট সিলেক্ট","code":"Ctrl + D"},{"definition":"পরের সেইম টেক্সট ডি-সিলেক্ট","code":"Ctrl + U"},{"definition":"বর্তমান সিলেক্ট স্কিপ","code":"Ctrl + K, D"},{"definition":"ব্র্যাকেটস এর কন্টেন্ট","code":"Ctrl + Shift + M"},{"definition":"ইন্ডেন্টেশনের কন্টেন্ট","code":"Ctrl + Shift + J"},{"definition":"কলাম সিলেকশন আপ","code":"Ctrl + Alt + আপ কী"},{"definition":"কলাম সিলেকশন ডাউন","code":"Ctrl + Alt + ডাউন কী"},{"definition":"একাধিক সিলেক্ট এডিট","code":"Ctrl + ক্লিক"}]},{"title":"এডিটিং","items":[{"definition":"লাইন ডিলেট করা","code":"Ctrl + Shift + K"},{"definition":"বর্তমান সিলেক্ট পয়েন্ট থেকে লাইনের শেষ পর্যন্ত ডিলেট করা","code":"Ctrl + K, K"},{"definition":"বর্তমান সিলেক্ট পয়েন্ট থেকে লাইনের বাউন্ডারি পর্যন্ত ডিলেট করা","code":"Ctrl + K, Backspace"},{"definition":"সামনের শব্দ ডিলেট করা","code":"Ctrl + Delete"},{"definition":"পিছনের শব্দ ডিলেট করা","code":"Ctrl + Backspace"},{"definition":"লাইন উপরে উঠানো","code":"Ctrl + Shift + আপ কী"},{"definition":"লাইন নিচে নামানো","code":"Ctrl + Shift + ডাউন কী"},{"definition":"লাইন আগে ঢুকানো","code":"Ctrl + Shift + Enter"},{"definition":"লাইন পরে ঢুকানো","code":"Ctrl + Enter"},{"definition":"বর্তমান লাইন ইন্ডেন্ট করা","code":"Ctrl + ]"},{"definition":"বর্তমান লাইনের ইন্ডেন্টশন সরানো","code":"Ctrl + ["},{"definition":"লাইন ডুপ্লিকেট করা","code":"Ctrl + Shift + D"},{"definition":"বর্তমানের লাইনের নিচে জয়েন করা","code":"Ctrl + J"},{"definition":"ঠিক ইন্ডেন্টেশন বজায় রেখে পেস্ট করা","code":"Ctrl + Shift + V"},{"definition":"ট্রান্সপোন্স","code":"সিলেক্ট আইটেম, Ctrl + T"}]},{"title":"ট্রান্সফর্ম","items":[{"definition":"বড় হাতের করা","code":"Ctrl + K, U"},{"definition":"ছোটো হাতের করা","code":"Ctrl + K, L"},{"definition":"ফন্ট সাইজ বাড়ানো","code":"Ctrl + +(যোগ চিহ্ন)"},{"definition":"ফন্ট সাইজ কমানো","code":"Ctrl + -(বিয়োগ চিহ্ন)"}]},{"title":"বুকমার্ক","items":[{"definition":"নতুন বুকমার্ক","code":"Ctrl + F2"},{"definition":"পরের বুকমার্ক","code":"F2"},{"definition":"আগের বুকমার্ক","code":"Shift + F2"},{"definition":"বুকমার্ক ক্লিয়ার","code":"Ctrl + Shift + F2"}]},{"title":"কোড ভাঁজ","items":[{"definition":"সিলেক্ট করা কোড ভাঁজ করা","code":"Ctrl + Shift + ["},{"definition":"সিলেক্ট করা ভাঁজ করা কোড দেখানো","code":"Ctrl + Shift + ]"},{"definition":"সবকিছু ভাঁজ করা","code":"Ctrl + K, 1"},{"definition":"সব ভাঁজ করা কোড দেখানো","code":"Ctrl + K, J"},{"definition":"ভাঁজ লেভেল","code":"Ctrl + 2/9"}]},{"title":"কমেন্ট","items":[{"definition":"লাইন কমেন্ট করা","code":"Ctrl + /"},{"definition":"ব্লক কমেন্ট","code":"Ctrl + Shift + /"}]}]},"filename":"shortcut-sblm3-win"}}